ARAMBHML/ARAMBHML.py
ARAMBHML/__init__.py
ARAMBHML-0.2.4.dist-info/LICENSE
ARAMBHML-0.2.4.dist-info/METADATA
ARAMBHML-0.2.4.dist-info/WHEEL
ARAMBHML-0.2.4.dist-info/top_level.txt
ARAMBHML-0.2.4.dist-info/RECORD
