Metadata-Version: 2.1
Name: ARAMBHML
Version: 0.2.4
Summary: An Auto ML framework that solves Classification Tasks
Home-page: UNKNOWN
Author: Amartya Bhattacharya,Rupam Kumar Roy
License: UNKNOWN
Keywords: auto ml,python,classification problem,machine learning
Platform: UNKNOWN
Classifier: Programming Language :: Python :: 3
Classifier: License :: OSI Approved :: MIT License
Classifier: Operating System :: OS Independent
Requires-Dist: pandas
Requires-Dist: numpy
Requires-Dist: matplotlib
Requires-Dist: seaborn
Requires-Dist: scikit-learn
Requires-Dist: sklearn-pandas
Requires-Dist: xgboost
Requires-Dist: plotly
Requires-Dist: plotly-express
